myaibot/__init__.py
myaibot/myaibot.py
myaibot-0.1.0.dist-info/METADATA
myaibot-0.1.0.dist-info/WHEEL
myaibot-0.1.0.dist-info/entry_points.txt
myaibot-0.1.0.dist-info/top_level.txt
myaibot-0.1.0.dist-info/RECORD
