Metadata-Version: 2.1
Name: myaibot
Version: 0.1.0
Summary: A myaibot using the OpenAI GPT-3 model
Home-page: https://github.com/syedhamidali/myaibot
Author: Hamid Ali Syed
Author-email: hamidsyed37@gmail.com
Classifier: Programming Language :: Python :: 3
Classifier: License :: OSI Approved :: MIT License
Classifier: Operating System :: OS Independent
Requires-Python: >=3.6
Requires-Dist: openai
